{"version":1,"resource":"vscode-remote://wsl%2Bubuntu/home/training/agus-app/resources/views/register/create.blade.php","entries":[{"id":"K3HW.php","timestamp":1692149532837},{"id":"hSxh.php","timestamp":1692149760867},{"id":"6G8o.php","timestamp":1692149800237},{"id":"YIra.php","timestamp":1692149814077},{"id":"qBeq.php","timestamp":1692149893067},{"id":"Mp7a.php","timestamp":1692150898807},{"id":"3ckX.php","timestamp":1692151122167},{"id":"Jfe9.php","timestamp":1692151311327},{"id":"K40t.php","timestamp":1692152874827},{"id":"kAjK.php","timestamp":1692153178807}]}